mldata/__init__.py
mldata/main.py
mldata/tests/__init__.py
mldata/tests/test_category_converter.py
mldata/tests/test_clearner.py
mldata/tests/test_helper.py
mldata/tests/test_normalizer.py
mldata/tests/test_processor.py
mldata/tests/outputs/__init__.py
python_module_starter-1.0.0.data/data/ReleaseNotes.md
python_module_starter-1.0.0.dist-info/DESCRIPTION.rst
python_module_starter-1.0.0.dist-info/METADATA
python_module_starter-1.0.0.dist-info/RECORD
python_module_starter-1.0.0.dist-info/WHEEL
python_module_starter-1.0.0.dist-info/metadata.json
python_module_starter-1.0.0.dist-info/top_level.txt
